AUTHORS.rst
LICENSE
MANIFEST.in
README.md
requirements.txt
setup.cfg
setup.py
sgai/__init__.py
sgai/sgai.py
sgai.egg-info/PKG-INFO
sgai.egg-info/SOURCES.txt
sgai.egg-info/dependency_links.txt
sgai.egg-info/not-zip-safe
sgai.egg-info/requires.txt
sgai.egg-info/top_level.txt
sgai/agent/__init__.py
sgai/agent/agent.py
sgai/agent/config.py
sgai/agent/data_helper.py
sgai/agent/model.py
sgai/agent/trainer.py