Metadata-Version: 2.1
Name: sgai
Version: 0.0.4
Summary: Simple Game AI package allows to easily define an interface     for a game and train a simple neural net to play it
Home-page: https://github.com/John15321/sgai
Author: Jan Bronicki
Author-email: janbronicki@gmail.com
License: MIT license
Keywords: sgai
Platform: UNKNOWN
Classifier: Development Status :: 2 - Pre-Alpha
Classifier: Intended Audience :: Developers
Classifier: License :: OSI Approved :: MIT License
Classifier: Natural Language :: English
Classifier: Programming Language :: Python :: 3.8
Classifier: Programming Language :: Python :: 3.9
Requires-Python: >=3.8
